cyclehunter/__init__.py
cyclehunter/core.py
cyclehunter/phik/__init__.py
cyclehunter/phik/cyclephik.py
cyclehunter-0.0.4.dist-info/LICENSE
cyclehunter-0.0.4.dist-info/METADATA
cyclehunter-0.0.4.dist-info/WHEEL
cyclehunter-0.0.4.dist-info/top_level.txt
cyclehunter-0.0.4.dist-info/RECORD
