Metadata-Version: 2.1
Name: cyclehunter
Version: 0.0.4
Summary: Framework for Discrete Nonlinear Dynamics and Chaos
Author: Matthew Gudorf and Ibrahim Abu-Hijleh
Author-email: matthew.gudorf@gmail.com
Keywords: pde,partial differential equation,numeric,numerical simulation,solver,framework,periodic cycle
Classifier: Development Status :: 5 - Production/Stable
Classifier: Intended Audience :: Science/Research
Classifier: Topic :: Scientific/Engineering :: Physics
Classifier: Programming Language :: Python :: 3
Classifier: Programming Language :: Python :: 3.8
Classifier: Programming Language :: Python :: 3.9
Classifier: License :: OSI Approved :: GNU General Public License v3 (GPLv3)
Classifier: Operating System :: Microsoft :: Windows :: Windows 10
Requires-Python: >=3.8
License-File: LICENSE
Requires-Dist: numpy
Requires-Dist: scipy
Provides-Extra: docs
Requires-Dist: ipython ; extra == 'docs'
Requires-Dist: sphinx (>=3.5.2) ; extra == 'docs'
Requires-Dist: sphinxcontrib-log-cabinet (>=1.0.1) ; extra == 'docs'
Requires-Dist: sphinx-issues (>=1.2.0) ; extra == 'docs'
Requires-Dist: sphinx-rtd-theme (>=0.5.1) ; extra == 'docs'
Requires-Dist: sphinx-gallery (>=0.8.2) ; extra == 'docs'
Requires-Dist: numpydoc (>=1.1) ; extra == 'docs'
Requires-Dist: pillow (>=8.0) ; extra == 'docs'
Requires-Dist: nb2plots (>=0.6) ; extra == 'docs'
Requires-Dist: texext (>=0.6.6) ; extra == 'docs'
